Metadata-Version: 2.1
Name: gsearch-nyaa
Version: 0.1.5
Summary: A Python Package for Automated Google Searches and Scraping of Search Results
Author: Praveen Senpai
Author-email: pvnt20@gmail.com
